dexipy/__init__.py
dexipy/analyse.py
dexipy/charts.py
dexipy/dexi.py
dexipy/eval.py
dexipy/parse.py
dexipy/types.py
dexipy/utils.py
dexipy/values.py
dexipy/tests/__init__.py
dexipy/tests/test_charts.py
dexipy/tests/test_dexi.py
dexipy/tests/test_eval.py
dexipy/tests/test_parse.py
dexipy/tests/test_utils.py
dexipy/tests/test_values.py
dexipy/tests/testdata.py
dexipy-1.0.0.dist-info/LICENSE.md
dexipy-1.0.0.dist-info/METADATA
dexipy-1.0.0.dist-info/WHEEL
dexipy-1.0.0.dist-info/top_level.txt
dexipy-1.0.0.dist-info/RECORD
