Metadata-Version: 2.1
Name: dexipy
Version: 1.0.0
Summary: A software package for using DEXi models in Python
Home-page: https://repo.ijs.si/markobohanec/dexipy
Author: Marko Bohanec
Author-email: marko.bohanec@ijs.si
License: LICENSE.md
Project-URL: Source, https://repo.ijs.si/markobohanec/dexipy
Project-URL: Documentation, https://dex.ijs.si/documentation/DEXiPy/
Keywords: Decision EXpert,DEX method,multi-criteria,decision model,MCDM
Requires-Python: >=3.7, <4
License-File: LICENSE.md
Requires-Dist: matplotlib
